cityfibre_opentelemetry/__init__.py
cityfibre_opentelemetry/environment_variables.py
cityfibre_opentelemetry/version.py
cityfibre_opentelemetry-0.1.8.dev0.dist-info/METADATA
cityfibre_opentelemetry-0.1.8.dev0.dist-info/WHEEL
cityfibre_opentelemetry-0.1.8.dev0.dist-info/entry_points.txt
cityfibre_opentelemetry-0.1.8.dev0.dist-info/licenses/LICENSE
cityfibre_opentelemetry-0.1.8.dev0.dist-info/RECORD
