Metadata-Version: 2.1
Name: cityfibre-opentelemetry
Version: 0.1.8.dev0
Summary: OpenTelemetry Python instrumentation
Project-URL: Homepage, https://github.com/ikmelnykova/cityfibre-opentelemetry
Author-email: Iryna Melnykova <ext_softserveinc_iryna.melnykova@cityfibre.com>
License-Expression: Apache-2.0
License-File: LICENSE
Classifier: Intended Audience :: Developers
Classifier: License :: OSI Approved :: Apache Software License
Classifier: Programming Language :: Python
Classifier: Programming Language :: Python :: 3
Classifier: Programming Language :: Python :: 3.8
Classifier: Programming Language :: Python :: 3.9
Classifier: Programming Language :: Python :: 3.10
Classifier: Programming Language :: Python :: 3.11
Requires-Python: >=3.8
Requires-Dist: opentelemetry-api==1.23.0
Requires-Dist: opentelemetry-exporter-otlp==1.23.0
Requires-Dist: opentelemetry-instrumentation-kafka-python==0.44b0
Requires-Dist: opentelemetry-instrumentation-requests==0.44b0
Requires-Dist: opentelemetry-sdk==1.23.0
Provides-Extra: test
